{
  "cli": {
    "version": ">= 16.15.0",
    "appVersionSource": "remote"
  },
  "build": {
    "development": {
      "developmentClient": true,
      "distribution": "internal",
      "cache": {
        "disabled": false
      }
    },
    "preview": {
      "distribution": "internal",
      "cache": {
        "disabled": false
      }
    },
    "production": {
      "autoIncrement": true,
      "cache": {
        "disabled": false
      },
      "ios": {
        "resourceClass": "m-medium",
        "buildConfiguration": "Release"
      }
    }
  },
  "submit": {
    "production": {}
  }
}
